{"skeleton":{"hash":"OHZrKGXXCu7qzUA7ypQix/MG/Fg","spine":"3.8.99","x":-378,"y":-200,"width":756,"height":410.04,"images":"","audio":""},"bones":[{"name":"root"},{"name":"gun","parent":"root","y":100.3},{"name":"","parent":"root","y":32},{"name":"gun_b","parent":"root","y":55.61},{"name":"eff","parent":"root","x":2.34,"y":24.22,"scaleX":0.5,"scaleY":0.5},{"name":"eff/eff_flame","parent":"root","y":95.66}],"slots":[{"name":"","bone":"root"},{"name":"","bone":""},{"name":"ae/aepng/","bone":"root","attachment":"ae/aepng/"},{"name":"gun_b","bone":"gun_b","attachment":"ae/aepng/gun_b/gun_b_00000"},{"name":"gun","bone":"gun","attachment":"ae/aepng/gun/gun_00000"},{"name":"pos","bone":"root"},{"name":"eff","bone":"eff","blend":"additive"},{"name":"eff/eff_flame","bone":"eff/eff_flame","blend":"additive"}],"skins":[{"name":"default","attachments":{"ae/aepng/":{"ae/aepng/":{"path":"body","x":30.7,"y":8.54,"width":284,"height":174}},"eff":{"eff/d01":{"width":128,"height":128},"eff/d02":{"width":128,"height":128},"eff/d03":{"width":128,"height":128},"eff/d04":{"width":128,"height":128},"eff/d05":{"width":128,"height":128},"eff/d06":{"width":128,"height":128},"eff/ef_com_alpha":{"width":2,"height":2}},"eff/eff_flame":{"eff/ef_com_alpha":{"width":2,"height":2},"eff/eff_flame2":{"y":118.19,"width":144,"height":132}},"gun":{"ae/aepng/gun/gun_00000":{"width":234,"height":210},"ae/aepng/gun/gun_00001":{"width":234,"height":210},"ae/aepng/gun/gun_00002":{"width":234,"height":210},"ae/aepng/gun/gun_00003":{"width":234,"height":210},"ae/aepng/gun/gun_00004":{"width":234,"height":210},"ae/aepng/gun/gun_00005":{"width":234,"height":210},"ae/aepng/gun/gun_00006":{"width":234,"height":210},"ae/aepng/gun/gun_00007":{"width":234,"height":210},"ae/aepng/gun/gun_00008":{"width":234,"height":210},"ae/aepng/gun/gun_00009":{"width":234,"height":210},"ae/aepng/gun/gun_00010":{"width":234,"height":210},"ae/aepng/gun/gun_00011":{"width":234,"height":210},"ae/aepng/gun/gun_00012":{"width":234,"height":210},"ae/aepng/gun/gun_00013":{"width":234,"height":210},"ae/aepng/gun/gun_00014":{"width":234,"height":210},"ae/aepng/gun/gun_00015":{"width":234,"height":210},"ae/aepng/gun/gun_00016":{"width":234,"height":210},"ae/aepng/gun/gun_00017":{"width":234,"height":210},"ae/aepng/gun/gun_00018":{"width":234,"height":210},"ae/aepng/gun/gun_00019":{"width":234,"height":210},"ae/aepng/gun/gun_00020":{"width":234,"height":210},"ae/aepng/gun/gun_00021":{"width":234,"height":210},"ae/aepng/gun/gun_00022":{"width":234,"height":210},"ae/aepng/gun/gun_00023":{"width":234,"height":210},"ae/aepng/gun/gun_00024":{"width":234,"height":210},"ae/aepng/gun/gun_00025":{"width":234,"height":210},"ae/aepng/gun/gun_00026":{"width":234,"height":210},"ae/aepng/gun/gun_00027":{"width":234,"height":210},"ae/aepng/gun/gun_00028":{"width":234,"height":210},"ae/aepng/gun/gun_00029":{"width":234,"height":210}},"gun_b":{"ae/aepng/gun_b/gun_b_00000":{"width":120,"height":104},"ae/aepng/gun_b/gun_b_00001":{"width":120,"height":104},"ae/aepng/gun_b/gun_b_00002":{"width":120,"height":104},"ae/aepng/gun_b/gun_b_00003":{"width":120,"height":104},"ae/aepng/gun_b/gun_b_00004":{"width":120,"height":104},"ae/aepng/gun_b/gun_b_00005":{"width":120,"height":104},"ae/aepng/gun_b/gun_b_00006":{"width":120,"height":104},"ae/aepng/gun_b/gun_b_00007":{"width":120,"height":104},"ae/aepng/gun_b/gun_b_00008":{"width":120,"height":104},"ae/aepng/gun_b/gun_b_00009":{"width":120,"height":104},"ae/aepng/gun_b/gun_b_00010":{"width":120,"height":104},"ae/aepng/gun_b/gun_b_00011":{"width":120,"height":104},"ae/aepng/gun_b/gun_b_00012":{"width":120,"height":104},"ae/aepng/gun_b/gun_b_00013":{"width":120,"height":104},"ae/aepng/gun_b/gun_b_00014":{"width":120,"height":104},"ae/aepng/gun_b/gun_b_00015":{"width":120,"height":104},"ae/aepng/gun_b/gun_b_00016":{"width":120,"height":104},"ae/aepng/gun_b/gun_b_00017":{"width":120,"height":104},"ae/aepng/gun_b/gun_b_00018":{"width":120,"height":104},"ae/aepng/gun_b/gun_b_00019":{"width":120,"height":104},"ae/aepng/gun_b/gun_b_00020":{"width":120,"height":104},"ae/aepng/gun_b/gun_b_00021":{"width":120,"height":104},"ae/aepng/gun_b/gun_b_00022":{"width":120,"height":104},"ae/aepng/gun_b/gun_b_00023":{"width":120,"height":104},"ae/aepng/gun_b/gun_b_00024":{"width":120,"height":104},"ae/aepng/gun_b/gun_b_00025":{"width":120,"height":104},"ae/aepng/gun_b/gun_b_00026":{"width":120,"height":104},"ae/aepng/gun_b/gun_b_00027":{"width":120,"height":104},"ae/aepng/gun_b/gun_b_00028":{"width":120,"height":104},"ae/aepng/gun_b/gun_b_00029":{"width":120,"height":104}}}}],"animations":{"attack_0":{"slots":{"eff":{"color":[{"time":0.1667,"color":"ffffffff"},{"time":1,"color":"ffffff00"}],"attachment":[{"name":"eff/ef_com_alpha"},{"time":0.1667,"name":"eff/d02"},{"time":0.3333,"name":"eff/d03"},{"time":0.5,"name":"eff/d04"},{"time":0.6667,"name":"eff/d05"},{"time":0.8333,"name":"eff/d06"},{"time":1,"name":"eff/d01"}]},"eff/eff_flame":{"color":[{"time":0.1667,"color":"ffffffff"},{"time":1,"color":"ffffff00"}],"attachment":[{"name":"eff/ef_com_alpha"},{"time":0.1667,"name":"eff/eff_flame2"}]},"gun":{"attachment":[{"name":"ae/aepng/gun/gun_00011"}]},"gun_b":{"attachment":[{"name":"ae/aepng/gun_b/gun_b_00011"}]},"":{"attachment":[{"name":null}]}},"bones":{"eff":{"translate":[{"x":-64,"y":112.82}],"scale":[{},{"time":1,"x":3,"y":3}]},"gun":{"translate":[{},{"time":0.1667,"x":-2.09,"y":0.71},{"time":1}]},"gun_b":{"translate":[{"x":-50.24,"y":70.72},{"time":0.1667,"x":-17.37,"y":55.05},{"time":1,"x":-50.24,"y":70.72}]},"eff/eff_flame":{"rotate":[{"angle":58.31}]}}},"attack_1":{"slots":{"eff":{"color":[{"time":0.1667,"color":"ffffffff"},{"time":1,"color":"ffffff00"}],"attachment":[{"name":"eff/ef_com_alpha"},{"time":0.1667,"name":"eff/d02"},{"time":0.3333,"name":"eff/d03"},{"time":0.5,"name":"eff/d04"},{"time":0.6667,"name":"eff/d05"},{"time":0.8333,"name":"eff/d06"},{"time":1,"name":"eff/d01"}]},"eff/eff_flame":{"color":[{"time":0.1667,"color":"ffffffff"},{"time":1,"color":"ffffff00"}],"attachment":[{"name":"eff/ef_com_alpha"},{"time":0.1667,"name":"eff/eff_flame2"}]},"gun":{"attachment":[{"name":"ae/aepng/gun/gun_00010"}]},"gun_b":{"attachment":[{"name":"ae/aepng/gun_b/gun_b_00010"}]},"":{"attachment":[{"name":null}]}},"bones":{"eff":{"translate":[{"x":-70.21,"y":96.26}],"scale":[{},{"time":1,"x":3,"y":3}]},"gun":{"translate":[{},{"time":0.1667,"x":-2.09,"y":0.71},{"time":1}]},"gun_b":{"translate":[{"x":-58.52,"y":63.68},{"time":0.1667,"x":-19.86,"y":51.74},{"time":1,"x":-58.52,"y":63.68}]},"eff/eff_flame":{"rotate":[{"angle":68.3}]}}},"attack_2":{"slots":{"eff":{"color":[{"time":0.1667,"color":"ffffffff"},{"time":1,"color":"ffffff00"}],"attachment":[{"name":"eff/ef_com_alpha"},{"time":0.1667,"name":"eff/d02"},{"time":0.3333,"name":"eff/d03"},{"time":0.5,"name":"eff/d04"},{"time":0.6667,"name":"eff/d05"},{"time":0.8333,"name":"eff/d06"},{"time":1,"name":"eff/d01"}]},"eff/eff_flame":{"color":[{"time":0.1667,"color":"ffffffff"},{"time":1,"color":"ffffff00"}],"attachment":[{"name":"eff/ef_com_alpha"},{"time":0.1667,"name":"eff/eff_flame2"}]},"gun":{"attachment":[{"name":"ae/aepng/gun/gun_00009"}]},"gun_b":{"attachment":[{"name":"ae/aepng/gun_b/gun_b_00009"}]},"":{"attachment":[{"name":null}]}},"bones":{"eff":{"translate":[{"x":-70.79,"y":88.23}],"scale":[{},{"time":1,"x":3,"y":3}]},"gun":{"translate":[{},{"time":0.1667,"x":-2.09,"y":0.71},{"time":1}]},"gun_b":{"translate":[{"x":-63.94,"y":55.42},{"time":0.1667,"x":-21.27,"y":47.6},{"time":1,"x":-63.94,"y":55.42}]},"eff/eff_flame":{"rotate":[{"angle":77.2}]}}},"attack_3":{"slots":{"eff":{"color":[{"time":0.1667,"color":"ffffffff"},{"time":1,"color":"ffffff00"}],"attachment":[{"name":"eff/ef_com_alpha"},{"time":0.1667,"name":"eff/d02"},{"time":0.3333,"name":"eff/d03"},{"time":0.5,"name":"eff/d04"},{"time":0.6667,"name":"eff/d05"},{"time":0.8333,"name":"eff/d06"},{"time":1,"name":"eff/d01"}]},"eff/eff_flame":{"color":[{"time":0.1667,"color":"ffffffff"},{"time":1,"color":"ffffff00"}],"attachment":[{"name":"eff/ef_com_alpha"},{"time":0.1667,"name":"eff/eff_flame2"}]},"gun":{"attachment":[{"name":"ae/aepng/gun/gun_00008"}]},"gun_b":{"attachment":[{"name":"ae/aepng/gun_b/gun_b_00008"}]},"":{"attachment":[{"name":null}]}},"bones":{"eff":{"translate":[{"x":-72.67,"y":76}],"scale":[{},{"time":1,"x":3,"y":3}]},"gun":{"translate":[{},{"time":0.1667,"x":-2.09,"y":-0.7},{"time":1}]},"gun_b":{"translate":[{"x":-66.29,"y":46.96},{"time":0.1667,"x":-20.33,"y":42.9},{"time":1,"x":-66.29,"y":46.96}]},"eff/eff_flame":{"rotate":[{"angle":85.5}]}}},"attack_4":{"slots":{"eff":{"color":[{"time":0.1667,"color":"ffffffff"},{"time":1,"color":"ffffff00"}],"attachment":[{"name":"eff/ef_com_alpha"},{"time":0.1667,"name":"eff/d02"},{"time":0.3333,"name":"eff/d03"},{"time":0.5,"name":"eff/d04"},{"time":0.6667,"name":"eff/d05"},{"time":0.8333,"name":"eff/d06"},{"time":1,"name":"eff/d01"}]},"eff/eff_flame":{"color":[{"time":0.1667,"color":"ffffffff"},{"time":1,"color":"ffffff00"}],"attachment":[{"name":"eff/ef_com_alpha"},{"time":0.1667,"name":"eff/eff_flame2"}]},"gun":{"attachment":[{"name":"ae/aepng/gun/gun_00007"}]},"gun_b":{"attachment":[{"name":"ae/aepng/gun_b/gun_b_00007"}]},"":{"attachment":[{"name":null}]}},"bones":{"eff":{"translate":[{"x":-65.3,"y":66.18}],"scale":[{},{"time":1,"x":3,"y":3}]},"gun":{"translate":[{},{"time":0.1667,"x":-2.09,"y":-0.7},{"time":1}]},"gun_b":{"translate":[{"x":-65.79,"y":39.1},{"time":0.1667,"x":-14.93,"y":37.99},{"time":1,"x":-62.67,"y":28.7}]},"eff/eff_flame":{"rotate":[{"angle":92.78}]}}},"attack_5":{"slots":{"eff":{"color":[{"time":0.1667,"color":"ffffffff"},{"time":1,"color":"ffffff00"}],"attachment":[{"name":"eff/ef_com_alpha"},{"time":0.1667,"name":"eff/d02"},{"time":0.3333,"name":"eff/d03"},{"time":0.5,"name":"eff/d04"},{"time":0.6667,"name":"eff/d05"},{"time":0.8333,"name":"eff/d06"},{"time":1,"name":"eff/d01"}]},"eff/eff_flame":{"color":[{"time":0.1667,"color":"ffffffff"},{"time":1,"color":"ffffff00"}],"attachment":[{"name":"eff/ef_com_alpha"},{"time":0.1667,"name":"eff/eff_flame2"}]},"gun":{"attachment":[{"name":"ae/aepng/gun/gun_00006"}]},"gun_b":{"attachment":[{"name":"ae/aepng/gun_b/gun_b_00006"}]},"":{"attachment":[{"name":null}]}},"bones":{"eff":{"translate":[{"x":-57.5,"y":42.26}],"scale":[{},{"time":1,"x":3,"y":3}]},"gun":{"translate":[{},{"time":0.1667,"x":-2.09,"y":-0.7},{"time":1}]},"gun_b":{"translate":[{"x":-62.67,"y":28.7},{"time":0.1667,"x":-14.93,"y":37.99},{"time":1,"x":-62.67,"y":28.7}]},"eff/eff_flame":{"rotate":[{"angle":100.47}]}}},"attack_6":{"slots":{"eff":{"color":[{"time":0.1667,"color":"ffffffff"},{"time":1,"color":"ffffff00"}],"attachment":[{"name":"eff/ef_com_alpha"},{"time":0.1667,"name":"eff/d02"},{"time":0.3333,"name":"eff/d03"},{"time":0.5,"name":"eff/d04"},{"time":0.6667,"name":"eff/d05"},{"time":0.8333,"name":"eff/d06"},{"time":1,"name":"eff/d01"}]},"eff/eff_flame":{"color":[{"time":0.1667,"color":"ffffffff"},{"time":1,"color":"ffffff00"}],"attachment":[{"name":"eff/ef_com_alpha"},{"time":0.1667,"name":"eff/eff_flame2"}]},"gun":{"attachment":[{"name":"ae/aepng/gun/gun_00005"}]},"gun_b":{"attachment":[{"name":"ae/aepng/gun_b/gun_b_00005"}]},"":{"attachment":[{"name":null}]}},"bones":{"eff":{"translate":[{"x":-64.43,"y":48.7}],"scale":[{},{"time":1,"x":3,"y":3}]},"gun":{"translate":[{},{"time":0.1667,"x":-2.09,"y":-0.7},{"time":1}]},"gun_b":{"translate":[{"x":-58.61,"y":21.26},{"time":0.1667,"x":-18.17,"y":35.22},{"time":1,"x":-58.61,"y":21.26}]},"eff/eff_flame":{"rotate":[{"angle":108.81}]}}},"attack_7":{"slots":{"eff":{"color":[{"time":0.1667,"color":"ffffffff"},{"time":1,"color":"ffffff00"}],"attachment":[{"name":"eff/ef_com_alpha"},{"time":0.1667,"name":"eff/d02"},{"time":0.3333,"name":"eff/d03"},{"time":0.5,"name":"eff/d04"},{"time":0.6667,"name":"eff/d05"},{"time":0.8333,"name":"eff/d06"},{"time":1,"name":"eff/d01"}]},"eff/eff_flame":{"color":[{"time":0.1667,"color":"ffffffff"},{"time":1,"color":"ffffff00"}],"attachment":[{"name":"eff/ef_com_alpha"},{"time":0.1667,"name":"eff/eff_flame2"}]},"gun":{"attachment":[{"name":"ae/aepng/gun/gun_00004"}]},"gun_b":{"attachment":[{"name":"ae/aepng/gun_b/gun_b_00004"}]},"":{"attachment":[{"name":null}]}},"bones":{"eff":{"translate":[{"x":-61.65,"y":38.63}],"scale":[{},{"time":1,"x":3,"y":3}]},"gun":{"translate":[{},{"time":0.1667,"x":-0.89,"y":-2.42},{"time":1}]},"gun_b":{"translate":[{"x":-50.19,"y":13.76},{"time":0.1667,"x":-6.61,"y":40.74},{"time":1,"x":-50.19,"y":13.76}]},"eff/eff_flame":{"rotate":[{"angle":118.39}]}}},"attack_8":{"slots":{"eff":{"color":[{"time":0.1667,"color":"ffffffff"},{"time":1,"color":"ffffff00"}],"attachment":[{"name":"eff/ef_com_alpha"},{"time":0.1667,"name":"eff/d02"},{"time":0.3333,"name":"eff/d03"},{"time":0.5,"name":"eff/d04"},{"time":0.6667,"name":"eff/d05"},{"time":0.8333,"name":"eff/d06"},{"time":1,"name":"eff/d01"}]},"eff/eff_flame":{"color":[{"time":0.1667,"color":"ffffffff"},{"time":1,"color":"ffffff00"}],"attachment":[{"name":"eff/ef_com_alpha"},{"time":0.1667,"name":"eff/eff_flame2"}]},"gun":{"attachment":[{"name":"ae/aepng/gun/gun_00003"}]},"gun_b":{"attachment":[{"name":"ae/aepng/gun_b/gun_b_00003"}]},"":{"attachment":[{"name":null}]}},"bones":{"eff":{"translate":[{"x":-67.21,"y":15.62}],"scale":[{},{"time":1,"x":3,"y":3}]},"gun":{"translate":[{},{"time":0.1667,"x":-0.89,"y":-2.42},{"time":1}]},"gun_b":{"translate":[{"x":-38.81,"y":8.83},{"time":0.1667,"x":-1.18,"y":30.34},{"time":1,"x":-27.43,"y":13.28}]},"eff/eff_flame":{"rotate":[{"angle":129.08}]}}},"attack_9":{"slots":{"eff":{"color":[{"time":0.1667,"color":"ffffffff"},{"time":1,"color":"ffffff00"}],"attachment":[{"name":"eff/ef_com_alpha"},{"time":0.1667,"name":"eff/d02"},{"time":0.3333,"name":"eff/d03"},{"time":0.5,"name":"eff/d04"},{"time":0.6667,"name":"eff/d05"},{"time":0.8333,"name":"eff/d06"},{"time":1,"name":"eff/d01"}]},"eff/eff_flame":{"color":[{"time":0.1667,"color":"ffffffff"},{"time":1,"color":"ffffff00"}],"attachment":[{"name":"eff/ef_com_alpha"},{"time":0.1667,"name":"eff/eff_flame2"}]},"gun":{"attachment":[{"name":"ae/aepng/gun/gun_00002"}]},"gun_b":{"attachment":[{"name":"ae/aepng/gun_b/gun_b_00002"}]}},"bones":{"eff":{"translate":[{"x":-26.23,"y":27.18}],"scale":[{},{"time":1,"x":3,"y":3}]},"gun":{"translate":[{},{"time":0.1667,"x":-0.89,"y":-2.42},{"time":1}]},"gun_b":{"translate":[{"x":-26.53,"y":4.03},{"time":0.1667,"x":-1.18,"y":30.34},{"time":1,"x":-26.53,"y":4.03}]},"eff/eff_flame":{"rotate":[{"angle":142.9}]}}},"attack_10":{"slots":{"eff":{"color":[{"time":0.1667,"color":"ffffffff"},{"time":1,"color":"ffffff00"}],"attachment":[{"name":"eff/ef_com_alpha"},{"time":0.1667,"name":"eff/d02"},{"time":0.3333,"name":"eff/d03"},{"time":0.5,"name":"eff/d04"},{"time":0.6667,"name":"eff/d05"},{"time":0.8333,"name":"eff/d06"},{"time":1,"name":"eff/d01"}]},"eff/eff_flame":{"color":[{"time":0.1667,"color":"ffffffff"},{"time":1,"color":"ffffff00"}],"attachment":[{"name":"eff/ef_com_alpha"},{"time":0.1667,"name":"eff/eff_flame2"}]},"gun":{"attachment":[{"name":"ae/aepng/gun/gun_00001"}]},"gun_b":{"attachment":[{"name":"ae/aepng/gun_b/gun_b_00001"}]},"":{"attachment":[{"name":null}]}},"bones":{"eff":{"translate":[{"x":-22.42}],"scale":[{},{"time":1,"x":3,"y":3}]},"gun":{"translate":[{},{"time":0.1667,"x":-0.89,"y":-2.42},{"time":1}]},"gun_b":{"translate":[{"x":-13.76,"y":1.98},{"time":0.1667,"y":22.49},{"time":1,"x":-13.76,"y":1.98}]},"eff/eff_flame":{"rotate":[{"angle":158.01}]}}},"attack_11":{"slots":{"eff":{"color":[{"time":0.1667,"color":"ffffffff"},{"time":1,"color":"ffffff00"}],"attachment":[{"name":"eff/ef_com_alpha"},{"time":0.1667,"name":"eff/d01"},{"time":0.3333,"name":"eff/d02"},{"time":0.5,"name":"eff/d03"},{"time":0.6667,"name":"eff/d04"},{"time":0.8333,"name":"eff/d05"},{"time":1,"name":"eff/d06"}]},"eff/eff_flame":{"color":[{"time":0.1667,"color":"ffffffff"},{"time":1,"color":"ffffff00"}],"attachment":[{"name":"eff/ef_com_alpha"},{"time":0.1667,"name":"eff/eff_flame2"}]}},"bones":{"eff":{"scale":[{},{"time":1,"x":3,"y":3}]},"gun":{"translate":[{},{"time":0.1667,"y":-2.42},{"time":1}]},"gun_b":{"translate":[{},{"time":0.1667,"y":23.09},{"time":1}]},"eff/eff_flame":{"rotate":[{"angle":175.98}]}}},"attack_12":{"slots":{"eff":{"color":[{"time":0.1667,"color":"ffffffff"},{"time":1,"color":"ffffff00"}],"attachment":[{"name":"eff/ef_com_alpha"},{"time":0.1667,"name":"eff/d02"},{"time":0.3333,"name":"eff/d03"},{"time":0.5,"name":"eff/d04"},{"time":0.6667,"name":"eff/d05"},{"time":0.8333,"name":"eff/d06"},{"time":1,"name":"eff/d01"}]},"eff/eff_flame":{"color":[{"time":0.1667,"color":"ffffffff"},{"time":1,"color":"ffffff00"}],"attachment":[{"name":"eff/ef_com_alpha"},{"time":0.1667,"name":"eff/eff_flame2"}]},"gun":{"attachment":[{"name":"ae/aepng/gun/gun_00029"}]},"gun_b":{"attachment":[{"name":"ae/aepng/gun_b/gun_b_00029"}]},"":{"attachment":[{"name":null}]}},"bones":{"eff":{"translate":[{"x":13.69,"y":30.74}],"scale":[{},{"time":1,"x":3,"y":3}]},"gun":{"translate":[{},{"time":0.1667,"x":-0.13,"y":-2.14},{"time":1}]},"gun_b":{"translate":[{"x":12.84,"y":1.26},{"time":0.1667,"x":4.12,"y":31.15},{"time":1,"x":12.84,"y":1.26}]},"eff/eff_flame":{"rotate":[{"angle":-165.61}]}}},"attack_13":{"slots":{"eff":{"color":[{"time":0.1667,"color":"ffffffff"},{"time":1,"color":"ffffff00"}],"attachment":[{"name":"eff/ef_com_alpha"},{"time":0.1667,"name":"eff/d02"},{"time":0.3333,"name":"eff/d03"},{"time":0.5,"name":"eff/d04"},{"time":0.6667,"name":"eff/d05"},{"time":0.8333,"name":"eff/d06"},{"time":1,"name":"eff/d01"}]},"eff/eff_flame":{"color":[{"time":0.1667,"color":"ffffffff"},{"time":1,"color":"ffffff00"}],"attachment":[{"name":"eff/ef_com_alpha"},{"time":0.1667,"name":"eff/eff_flame2"}]},"gun":{"attachment":[{"name":"ae/aepng/gun/gun_00028"}]},"gun_b":{"attachment":[{"name":"ae/aepng/gun_b/gun_b_00028"}]},"":{"attachment":[{"name":null}]}},"bones":{"eff":{"translate":[{"x":29.65,"y":35.19}],"scale":[{},{"time":1,"x":3,"y":3}]},"gun":{"translate":[{},{"time":0.1667,"x":0.45,"y":-1.04},{"time":1}]},"gun_b":{"translate":[{"x":26.07,"y":3.02},{"time":0.1667,"x":7.21,"y":32.03},{"time":1,"x":26.07,"y":3.02}]},"eff/eff_flame":{"rotate":[{"angle":-148.77}]}}},"attack_14":{"slots":{"eff":{"color":[{"time":0.1667,"color":"ffffffff"},{"time":1,"color":"ffffff00"}],"attachment":[{"name":"eff/ef_com_alpha"},{"time":0.1667,"name":"eff/d02"},{"time":0.3333,"name":"eff/d03"},{"time":0.5,"name":"eff/d04"},{"time":0.6667,"name":"eff/d05"},{"time":0.8333,"name":"eff/d06"},{"time":1,"name":"eff/d01"}]},"eff/eff_flame":{"color":[{"time":0.1667,"color":"ffffffff"},{"time":1,"color":"ffffff00"}],"attachment":[{"name":"eff/ef_com_alpha"},{"time":0.1667,"name":"eff/eff_flame2"}]},"gun":{"attachment":[{"name":"ae/aepng/gun/gun_00027"}]},"gun_b":{"attachment":[{"name":"ae/aepng/gun_b/gun_b_00027"}]},"":{"attachment":[{"name":null}]}},"bones":{"eff":{"translate":[{"x":41.37,"y":39.66}],"scale":[{},{"time":1,"x":3,"y":3}]},"gun":{"translate":[{},{"time":0.1667,"x":1.15,"y":-0.34},{"time":1}]},"gun_b":{"translate":[{"x":37.4,"y":9.75},{"time":0.1667,"x":10.39,"y":34.51},{"time":1,"x":37.4,"y":9.75}]},"eff/eff_flame":{"rotate":[{"angle":-134.33}]}}},"attack_15":{"slots":{"eff":{"color":[{"time":0.1667,"color":"ffffffff"},{"time":1,"color":"ffffff00"}],"attachment":[{"name":"eff/ef_com_alpha"},{"time":0.1667,"name":"eff/d02"},{"time":0.3333,"name":"eff/d03"},{"time":0.5,"name":"eff/d04"},{"time":0.6667,"name":"eff/d05"},{"time":0.8333,"name":"eff/d06"},{"time":1,"name":"eff/d01"}]},"eff/eff_flame":{"color":[{"time":0.1667,"color":"ffffffff"},{"time":1,"color":"ffffff00"}],"attachment":[{"name":"eff/ef_com_alpha"},{"time":0.1667,"name":"eff/eff_flame2"}]},"gun":{"attachment":[{"name":"ae/aepng/gun/gun_00026"}]},"gun_b":{"attachment":[{"name":"ae/aepng/gun_b/gun_b_00026"}]},"":{"attachment":[{"name":null}]}},"bones":{"eff":{"translate":[{"x":52.36,"y":42.53}],"scale":[{},{"time":1,"x":3,"y":3}]},"gun":{"translate":[{},{"time":0.1667,"x":1.15,"y":-0.34},{"time":1}]},"gun_b":{"translate":[{"x":48.42,"y":14.6},{"time":0.1667,"x":12.39,"y":31.32},{"time":1,"x":48.42,"y":14.6}]},"eff/eff_flame":{"rotate":[{"angle":-122.88}]}}},"attack_16":{"slots":{"eff":{"color":[{"time":0.1667,"color":"ffffffff"},{"time":1,"color":"ffffff00"}],"attachment":[{"name":"eff/ef_com_alpha"},{"time":0.1667,"name":"eff/d02"},{"time":0.3333,"name":"eff/d03"},{"time":0.5,"name":"eff/d04"},{"time":0.6667,"name":"eff/d05"},{"time":0.8333,"name":"eff/d06"},{"time":1,"name":"eff/d01"}]},"eff/eff_flame":{"color":[{"time":0.1667,"color":"ffffffff"},{"time":1,"color":"ffffff00"}],"attachment":[{"name":"eff/ef_com_alpha"},{"time":0.1667,"name":"eff/eff_flame2"}]},"gun":{"attachment":[{"name":"ae/aepng/gun/gun_00025"}]},"gun_b":{"attachment":[{"name":"ae/aepng/gun_b/gun_b_00025"}]},"":{"attachment":[{"name":null}]}},"bones":{"eff":{"translate":[{"x":61.18,"y":53.55}],"scale":[{},{"time":1,"x":3,"y":3}]},"gun":{"translate":[{},{"time":0.1667,"x":1.15,"y":-0.34},{"time":1}]},"gun_b":{"translate":[{"x":55.68,"y":21.45},{"time":0.1667,"x":16.42,"y":36.96},{"time":1,"x":55.68,"y":21.45}]},"eff/eff_flame":{"rotate":[{"angle":-113.08}]}}},"attack_17":{"slots":{"eff":{"color":[{"time":0.1667,"color":"ffffffff"},{"time":1,"color":"ffffff00"}],"attachment":[{"name":"eff/ef_com_alpha"},{"time":0.1667,"name":"eff/d02"},{"time":0.3333,"name":"eff/d03"},{"time":0.5,"name":"eff/d04"},{"time":0.6667,"name":"eff/d05"},{"time":0.8333,"name":"eff/d06"},{"time":1,"name":"eff/d01"}]},"eff/eff_flame":{"color":[{"time":0.1667,"color":"ffffffff"},{"time":1,"color":"ffffff00"}],"attachment":[{"name":"eff/ef_com_alpha"},{"time":0.1667,"name":"eff/eff_flame2"}]},"gun":{"attachment":[{"name":"ae/aepng/gun/gun_00024"}]},"gun_b":{"attachment":[{"name":"ae/aepng/gun_b/gun_b_00024"}]},"":{"attachment":[{"name":null}]}},"bones":{"eff":{"translate":[{"x":65.21,"y":60.4}],"scale":[{},{"time":1,"x":3,"y":3}]},"gun":{"translate":[{},{"time":0.1667,"x":1.15,"y":-0.34},{"time":1}]},"gun_b":{"translate":[{"x":61.04,"y":29.71},{"time":0.1667,"x":16.42,"y":39.44},{"time":1,"x":61.04,"y":29.71}]},"eff/eff_flame":{"rotate":[{"angle":-103.78}]}}},"attack_18":{"slots":{"eff":{"color":[{"time":0.1667,"color":"ffffffff"},{"time":1,"color":"ffffff00"}],"attachment":[{"name":"eff/ef_com_alpha"},{"time":0.1667,"name":"eff/d02"},{"time":0.3333,"name":"eff/d03"},{"time":0.5,"name":"eff/d04"},{"time":0.6667,"name":"eff/d05"},{"time":0.8333,"name":"eff/d06"},{"time":1,"name":"eff/d01"}]},"eff/eff_flame":{"color":[{"time":0.1667,"color":"ffffffff"},{"time":1,"color":"ffffff00"}],"attachment":[{"name":"eff/ef_com_alpha"},{"time":0.1667,"name":"eff/eff_flame2"}]},"gun":{"attachment":[{"name":"ae/aepng/gun/gun_00023"}]},"gun_b":{"attachment":[{"name":"ae/aepng/gun_b/gun_b_00023"}]},"":{"attachment":[{"name":null}]}},"bones":{"eff":{"translate":[{"x":65.21,"y":70.5}],"scale":[{},{"time":1,"x":3,"y":3}]},"gun":{"translate":[{},{"time":0.1667,"x":1.15,"y":0.76},{"time":1}]},"gun_b":{"translate":[{"x":64.07,"y":37.79},{"time":0.1667,"x":16.42,"y":40.45},{"time":1,"x":64.07,"y":37.79}]},"eff/eff_flame":{"rotate":[{"angle":-95.66}]}}},"attack_19":{"slots":{"eff":{"color":[{"time":0.1667,"color":"ffffffff"},{"time":1,"color":"ffffff00"}],"attachment":[{"name":"eff/ef_com_alpha"},{"time":0.1667,"name":"eff/d02"},{"time":0.3333,"name":"eff/d03"},{"time":0.5,"name":"eff/d04"},{"time":0.6667,"name":"eff/d05"},{"time":0.8333,"name":"eff/d06"},{"time":1,"name":"eff/d01"}]},"eff/eff_flame":{"color":[{"time":0.1667,"color":"ffffffff"},{"time":1,"color":"ffffff00"}],"attachment":[{"name":"eff/ef_com_alpha"},{"time":0.1667,"name":"eff/eff_flame2"}]},"gun":{"attachment":[{"name":"ae/aepng/gun/gun_00022"}]},"gun_b":{"attachment":[{"name":"ae/aepng/gun_b/gun_b_00022"}]},"":{"attachment":[{"name":null}]}},"bones":{"eff":{"translate":[{"x":64.2,"y":79.59}],"scale":[{},{"time":1,"x":3,"y":3}]},"gun":{"translate":[{},{"time":0.1667,"x":1.15,"y":0.76},{"time":1}]},"gun_b":{"translate":[{"x":63.72,"y":46.92},{"time":0.1667,"x":15.71,"y":46.06},{"time":1,"x":63.72,"y":46.92}]},"eff/eff_flame":{"rotate":[{"angle":-87.48}]}}},"attack_20":{"slots":{"eff":{"color":[{"time":0.1667,"color":"ffffffff"},{"time":1,"color":"ffffff00"}],"attachment":[{"name":"eff/ef_com_alpha"},{"time":0.1667,"name":"eff/d02"},{"time":0.3333,"name":"eff/d03"},{"time":0.5,"name":"eff/d04"},{"time":0.6667,"name":"eff/d05"},{"time":0.8333,"name":"eff/d06"},{"time":1,"name":"eff/d01"}]},"eff/eff_flame":{"color":[{"time":0.1667,"color":"ffffffff"},{"time":1,"color":"ffffff00"}],"attachment":[{"name":"eff/ef_com_alpha"},{"time":0.1667,"name":"eff/eff_flame2"}]},"gun":{"attachment":[{"name":"ae/aepng/gun/gun_00021"}]},"gun_b":{"attachment":[{"name":"ae/aepng/gun_b/gun_b_00021"}]},"":{"attachment":[{"name":null}]}},"bones":{"eff":{"translate":[{"x":62.44,"y":89.42}],"scale":[{},{"time":1,"x":3,"y":3}]},"gun":{"translate":[{},{"time":0.1667,"x":1.15,"y":0.76},{"time":1}]},"gun_b":{"translate":[{"x":61.27,"y":55.34},{"time":0.1667,"x":13.96,"y":46.77},{"time":1,"x":61.27,"y":55.34}]},"eff/eff_flame":{"rotate":[{"angle":-79.82}]}}},"attack_21":{"slots":{"eff":{"color":[{"time":0.1667,"color":"ffffffff"},{"time":1,"color":"ffffff00"}],"attachment":[{"name":"eff/ef_com_alpha"},{"time":0.1667,"name":"eff/d02"},{"time":0.3333,"name":"eff/d03"},{"time":0.5,"name":"eff/d04"},{"time":0.6667,"name":"eff/d05"},{"time":0.8333,"name":"eff/d06"},{"time":1,"name":"eff/d01"}]},"eff/eff_flame":{"color":[{"time":0.1667,"color":"ffffffff"},{"time":1,"color":"ffffff00"}],"attachment":[{"name":"eff/ef_com_alpha"},{"time":0.1667,"name":"eff/eff_flame2"}]},"gun":{"attachment":[{"name":"ae/aepng/gun/gun_00020"}]},"gun_b":{"attachment":[{"name":"ae/aepng/gun_b/gun_b_00020"}]},"":{"attachment":[{"name":null}]}},"bones":{"eff":{"translate":[{"x":58.39,"y":111.97}],"scale":[{},{"time":1,"x":3,"y":3}]},"gun":{"translate":[{},{"time":0.1667,"x":1.15,"y":0.76},{"time":1}]},"gun_b":{"translate":[{"x":55.03,"y":63.45},{"time":0.1667,"x":13.34,"y":46.14},{"time":1,"x":55.03,"y":63.45}]},"eff/eff_flame":{"rotate":[{"angle":-71.05}]}}},"attack_22":{"slots":{"eff":{"color":[{"time":0.1667,"color":"ffffffff"},{"time":1,"color":"ffffff00"}],"attachment":[{"name":"eff/ef_com_alpha"},{"time":0.1667,"name":"eff/d02"},{"time":0.3333,"name":"eff/d03"},{"time":0.5,"name":"eff/d04"},{"time":0.6667,"name":"eff/d05"},{"time":0.8333,"name":"eff/d06"},{"time":1,"name":"eff/d01"}]},"eff/eff_flame":{"color":[{"time":0.1667,"color":"ffffffff"},{"time":1,"color":"ffffff00"}],"attachment":[{"name":"eff/ef_com_alpha"},{"time":0.1667,"name":"eff/eff_flame2"}]},"gun":{"attachment":[{"name":"ae/aepng/gun/gun_00019"}]},"gun_b":{"attachment":[{"name":"ae/aepng/gun_b/gun_b_00019"}]},"":{"attachment":[{"name":null}]}},"bones":{"eff":{"translate":[{"x":58.39,"y":111.97}],"scale":[{},{"time":1,"x":3,"y":3}]},"gun":{"translate":[{},{"time":0.1667,"x":0.26,"y":0.88},{"time":1}]},"gun_b":{"translate":[{"x":47.08,"y":69.18},{"time":0.1667,"x":11.11,"y":47.41},{"time":1,"x":47.08,"y":69.18}]},"eff/eff_flame":{"rotate":[{"angle":-62.13}]}}},"attack_23":{"slots":{"eff":{"color":[{"time":0.1667,"color":"ffffffff"},{"time":1,"color":"ffffff00"}],"attachment":[{"name":"eff/ef_com_alpha"},{"time":0.1667,"name":"eff/d02"},{"time":0.3333,"name":"eff/d03"},{"time":0.5,"name":"eff/d04"},{"time":0.6667,"name":"eff/d05"},{"time":0.8333,"name":"eff/d06"},{"time":1,"name":"eff/d01"}]},"eff/eff_flame":{"color":[{"time":0.1667,"color":"ffffffff"},{"time":1,"color":"ffffff00"}],"attachment":[{"name":"eff/ef_com_alpha"},{"time":0.1667,"name":"eff/eff_flame2"}]},"gun":{"attachment":[{"name":"ae/aepng/gun/gun_00018"}]},"gun_b":{"attachment":[{"name":"ae/aepng/gun_b/gun_b_00018"}]},"":{"attachment":[{"name":null}]}},"bones":{"eff":{"translate":[{"x":45.71,"y":120.95}],"scale":[{},{"time":1,"x":3,"y":3}]},"gun":{"translate":[{},{"time":0.1667,"x":0.26,"y":1.21},{"time":1}]},"gun_b":{"translate":[{"x":37.53,"y":75.05},{"time":0.1667,"x":9.64,"y":51.08},{"time":1,"x":37.53,"y":75.05}]},"eff/eff_flame":{"rotate":[{"angle":-51.52}]}}},"attack_24":{"slots":{"eff":{"color":[{"time":0.1667,"color":"ffffffff"},{"time":1,"color":"ffffff00"}],"attachment":[{"name":"eff/ef_com_alpha"},{"time":0.1667,"name":"eff/d02"},{"time":0.3333,"name":"eff/d03"},{"time":0.5,"name":"eff/d04"},{"time":0.6667,"name":"eff/d05"},{"time":0.8333,"name":"eff/d06"},{"time":1,"name":"eff/d01"}]},"eff/eff_flame":{"color":[{"time":0.1667,"color":"ffffffff"},{"time":1,"color":"ffffff00"}],"attachment":[{"name":"eff/ef_com_alpha"},{"time":0.1667,"name":"eff/eff_flame2"}]},"gun":{"attachment":[{"name":"ae/aepng/gun/gun_00017"}]},"gun_b":{"attachment":[{"name":"ae/aepng/gun_b/gun_b_00017"}]},"":{"attachment":[{"name":null}]}},"bones":{"eff":{"translate":[{"x":31.4,"y":128.65}],"scale":[{},{"time":1,"x":3,"y":3}]},"gun":{"translate":[{},{"time":0.1667,"x":0.26,"y":1.21},{"time":1}]},"gun_b":{"translate":[{"x":25.06,"y":80.19},{"time":0.1667,"x":6.71,"y":53.65},{"time":1,"x":25.06,"y":80.19}]},"eff/eff_flame":{"rotate":[{"angle":-38.32}]}}},"attack_25":{"slots":{"eff":{"color":[{"time":0.1667,"color":"ffffffff"},{"time":1,"color":"ffffff00"}],"attachment":[{"name":"eff/ef_com_alpha"},{"time":0.1667,"name":"eff/d02"},{"time":0.3333,"name":"eff/d03"},{"time":0.5,"name":"eff/d04"},{"time":0.6667,"name":"eff/d05"},{"time":0.8333,"name":"eff/d06"},{"time":1,"name":"eff/d01"}]},"eff/eff_flame":{"color":[{"time":0.1667,"color":"ffffffff"},{"time":1,"color":"ffffff00"}],"attachment":[{"name":"eff/ef_com_alpha"},{"time":0.1667,"name":"eff/eff_flame2"}]},"gun":{"attachment":[{"name":"ae/aepng/gun/gun_00016"}]},"gun_b":{"attachment":[{"name":"ae/aepng/gun_b/gun_b_00016"}]},"":{"attachment":[{"name":null}]}},"bones":{"eff":{"translate":[{"x":14.16,"y":131.19}],"scale":[{},{"time":1,"x":3,"y":3}]},"gun":{"translate":[{},{"time":0.1667,"y":1.21},{"time":1}]},"gun_b":{"translate":[{"x":13.13,"y":83.63},{"time":0.1667,"x":2.2,"y":56.57},{"time":1,"x":13.13,"y":83.63}]},"eff/eff_flame":{"rotate":[{"angle":-22.27}]}}},"attack_26":{"slots":{"eff":{"color":[{"time":0.1667,"color":"ffffffff"},{"time":1,"color":"ffffff00"}],"attachment":[{"name":"eff/ef_com_alpha"},{"time":0.1667,"name":"eff/d02"},{"time":0.3333,"name":"eff/d03"},{"time":0.5,"name":"eff/d04"},{"time":0.6667,"name":"eff/d05"},{"time":0.8333,"name":"eff/d06"},{"time":1,"name":"eff/d01"}]},"eff/eff_flame":{"color":[{"time":0.1667,"color":"ffffffff"},{"time":1,"color":"ffffff00"}],"attachment":[{"name":"eff/ef_com_alpha"},{"time":0.1667,"name":"eff/eff_flame2"}]},"gun":{"attachment":[{"name":"ae/aepng/gun/gun_00015"}]},"gun_b":{"attachment":[{"name":"ae/aepng/gun_b/gun_b_00015"}]},"":{"attachment":[{"name":null}]}},"bones":{"eff":{"translate":[{"x":-3.16,"y":131.19}],"scale":[{},{"time":1,"x":3,"y":3}]},"gun":{"translate":[{},{"time":0.1667,"y":1.21},{"time":1}]},"gun_b":{"translate":[{"x":-1.11,"y":83.25},{"time":0.1667,"x":-1.26,"y":56.57},{"time":1,"x":-1.11,"y":83.25}]},"eff/eff_flame":{"rotate":[{"angle":-4.37}]}}},"attack_27":{"slots":{"eff":{"color":[{"time":0.1667,"color":"ffffffff"},{"time":1,"color":"ffffff00"}],"attachment":[{"name":"eff/ef_com_alpha"},{"time":0.1667,"name":"eff/d02"},{"time":0.3333,"name":"eff/d03"},{"time":0.5,"name":"eff/d04"},{"time":0.6667,"name":"eff/d05"},{"time":0.8333,"name":"eff/d06"},{"time":1,"name":"eff/d01"}]},"eff/eff_flame":{"color":[{"time":0.1667,"color":"ffffffff"},{"time":1,"color":"ffffff00"}],"attachment":[{"name":"eff/ef_com_alpha"},{"time":0.1667,"name":"eff/eff_flame2"}]},"gun":{"attachment":[{"name":"ae/aepng/gun/gun_00014"}]},"gun_b":{"attachment":[{"name":"ae/aepng/gun_b/gun_b_00014"}]},"":{"attachment":[{"name":null}]}},"bones":{"eff":{"translate":[{"x":-15.34,"y":120.75}],"scale":[{},{"time":1,"x":3,"y":3}]},"gun":{"translate":[{},{"time":0.1667,"x":-0.87,"y":0.71},{"time":1}]},"gun_b":{"translate":[{"x":-15.18,"y":82.44},{"time":0.1667,"x":-8.1,"y":62.6},{"time":1,"x":-15.18,"y":82.44}]},"eff/eff_flame":{"rotate":[{"angle":14.09}]}}},"attack_28":{"slots":{"eff":{"color":[{"time":0.1667,"color":"ffffffff"},{"time":1,"color":"ffffff00"}],"attachment":[{"name":"eff/ef_com_alpha"},{"time":0.1667,"name":"eff/d02"},{"time":0.3333,"name":"eff/d03"},{"time":0.5,"name":"eff/d04"},{"time":0.6667,"name":"eff/d05"},{"time":0.8333,"name":"eff/d06"},{"time":1,"name":"eff/d01"}]},"eff/eff_flame":{"color":[{"time":0.1667,"color":"ffffffff"},{"time":1,"color":"ffffff00"}],"attachment":[{"name":"eff/ef_com_alpha"},{"time":0.1667,"name":"eff/eff_flame2"}]},"gun":{"attachment":[{"name":"ae/aepng/gun/gun_00013"}]},"gun_b":{"attachment":[{"name":"ae/aepng/gun_b/gun_b_00013"}]},"":{"attachment":[{"name":null}]}},"bones":{"eff":{"translate":[{"x":-29.97,"y":117.24}],"scale":[{},{"time":1,"x":3,"y":3}]},"gun":{"translate":[{},{"time":0.1667,"x":-0.87,"y":0.71},{"time":1}]},"gun_b":{"translate":[{"x":-27.17,"y":80.6},{"time":0.1667,"x":-14.55,"y":63.52},{"time":1,"x":-27.17,"y":80.6}]},"eff/eff_flame":{"rotate":[{"angle":31.17}]}}},"attack_29":{"slots":{"eff":{"color":[{"time":0.1667,"color":"ffffffff"},{"time":1,"color":"ffffff00"}],"attachment":[{"name":"eff/ef_com_alpha"},{"time":0.1667,"name":"eff/d02"},{"time":0.3333,"name":"eff/d03"},{"time":0.5,"name":"eff/d04"},{"time":0.6667,"name":"eff/d05"},{"time":0.8333,"name":"eff/d06"},{"time":1,"name":"eff/d01"}]},"eff/eff_flame":{"color":[{"time":0.1667,"color":"ffffffff"},{"time":1,"color":"ffffff00"}],"attachment":[{"name":"eff/ef_com_alpha"},{"time":0.1667,"name":"eff/eff_flame2"}]},"gun":{"attachment":[{"name":"ae/aepng/gun/gun_00012"}]},"gun_b":{"attachment":[{"name":"ae/aepng/gun_b/gun_b_00012"}]},"":{"attachment":[{"name":null}]}},"bones":{"eff":{"translate":[{"x":-50.25,"y":118.25}],"scale":[{},{"time":1,"x":3,"y":3}]},"gun":{"translate":[{},{"time":0.1667,"x":-0.87,"y":0.71},{"time":1}]},"gun_b":{"translate":[{"x":-39.84,"y":77.05},{"time":0.1667,"x":-15.57,"y":60.48},{"time":1,"x":-39.84,"y":77.05}]},"eff/eff_flame":{"rotate":[{"angle":45.73}]}}},"idle_0":{"slots":{"gun":{"attachment":[{"name":"ae/aepng/gun/gun_00011"}]},"gun_b":{"attachment":[{"name":"ae/aepng/gun_b/gun_b_00011"}]},"":{"attachment":[{"name":null}]}},"bones":{"gun_b":{"translate":[{"x":-50.64,"y":70.99}]}}},"idle_1":{"slots":{"gun":{"attachment":[{"name":"ae/aepng/gun/gun_00010"}]},"gun_b":{"attachment":[{"name":"ae/aepng/gun_b/gun_b_00010"}]},"":{"attachment":[{"name":null}]}},"bones":{"gun_b":{"translate":[{"x":-59.4,"y":64.43}]}}},"idle_2":{"slots":{"gun":{"attachment":[{"name":"ae/aepng/gun/gun_00009"}]},"gun_b":{"attachment":[{"name":"ae/aepng/gun_b/gun_b_00009"}]},"":{"attachment":[{"name":null}]}},"bones":{"gun_b":{"translate":[{"x":-64.32,"y":55.67}]}}},"idle_3":{"slots":{"gun":{"attachment":[{"name":"ae/aepng/gun/gun_00008"}]},"gun_b":{"attachment":[{"name":"ae/aepng/gun_b/gun_b_00008"}]},"":{"attachment":[{"name":null}]}},"bones":{"gun_b":{"translate":[{"x":-66.51,"y":47.47}]}}},"idle_4":{"slots":{"gun":{"attachment":[{"name":"ae/aepng/gun/gun_00007"}]},"gun_b":{"attachment":[{"name":"ae/aepng/gun_b/gun_b_00007"}]},"":{"attachment":[{"name":null}]}},"bones":{"gun_b":{"translate":[{"x":-65.96,"y":37.62}]}}},"idle_5":{"slots":{"gun":{"attachment":[{"name":"ae/aepng/gun/gun_00006"}]},"gun_b":{"attachment":[{"name":"ae/aepng/gun_b/gun_b_00006"}]},"":{"attachment":[{"name":null}]}},"bones":{"gun_b":{"translate":[{"x":-62.68,"y":30.51}]}}},"idle_6":{"slots":{"gun":{"attachment":[{"name":"ae/aepng/gun/gun_00005"}]},"gun_b":{"attachment":[{"name":"ae/aepng/gun_b/gun_b_00005"}]},"":{"attachment":[{"name":null}]}},"bones":{"gun_b":{"translate":[{"x":-57.21,"y":21.76}]}}},"idle_7":{"slots":{"gun":{"attachment":[{"name":"ae/aepng/gun/gun_00004"}]},"gun_b":{"attachment":[{"name":"ae/aepng/gun_b/gun_b_00004"}]},"":{"attachment":[{"name":null}]}},"bones":{"gun_b":{"translate":[{"x":-49,"y":15.19}]}}},"idle_8":{"slots":{"gun":{"attachment":[{"name":"ae/aepng/gun/gun_00003"}]},"gun_b":{"attachment":[{"name":"ae/aepng/gun_b/gun_b_00003"}]},"":{"attachment":[{"name":null}]}},"bones":{"gun_b":{"translate":[{"x":-38.53,"y":8.6}]}}},"idle_9":{"slots":{"gun":{"attachment":[{"name":"ae/aepng/gun/gun_00002"}]},"gun_b":{"attachment":[{"name":"ae/aepng/gun_b/gun_b_00002"}]}},"bones":{"gun_b":{"translate":[{"x":-27.55,"y":3.84}]}}},"idle_10":{"slots":{"gun":{"attachment":[{"name":"ae/aepng/gun/gun_00001"}]},"gun_b":{"attachment":[{"name":"ae/aepng/gun_b/gun_b_00001"}]}},"bones":{"gun_b":{"translate":[{"x":-10.91,"y":2.73}]}}},"idle_11":{},"idle_12":{"slots":{"gun":{"attachment":[{"name":"ae/aepng/gun/gun_00029"}]},"gun_b":{"attachment":[{"name":"ae/aepng/gun_b/gun_b_00029"}]},"":{"attachment":[{"name":null}]}},"bones":{"gun_b":{"translate":[{"x":13.12,"y":1.68}]}}},"idle_13":{"slots":{"gun":{"attachment":[{"name":"ae/aepng/gun/gun_00028"}]},"gun_b":{"attachment":[{"name":"ae/aepng/gun_b/gun_b_00028"}]},"":{"attachment":[{"name":null}]}},"bones":{"gun_b":{"translate":[{"x":25.15,"y":5.17}]}}},"idle_14":{"slots":{"gun":{"attachment":[{"name":"ae/aepng/gun/gun_00027"}]},"gun_b":{"attachment":[{"name":"ae/aepng/gun_b/gun_b_00027"}]},"":{"attachment":[{"name":null}]}},"bones":{"gun_b":{"translate":[{"x":37.28,"y":7.82}]}}},"idle_15":{"slots":{"gun":{"attachment":[{"name":"ae/aepng/gun/gun_00026"}]},"gun_b":{"attachment":[{"name":"ae/aepng/gun_b/gun_b_00026"}]},"":{"attachment":[{"name":null}]}},"bones":{"gun_b":{"translate":[{"x":48.27,"y":13.88}]}}},"idle_16":{"slots":{"gun":{"attachment":[{"name":"ae/aepng/gun/gun_00025"}]},"gun_b":{"attachment":[{"name":"ae/aepng/gun_b/gun_b_00025"}]},"":{"attachment":[{"name":null}]}},"bones":{"gun_b":{"translate":[{"x":55.09,"y":21.84}]}}},"idle_17":{"slots":{"gun":{"attachment":[{"name":"ae/aepng/gun/gun_00024"}]},"gun_b":{"attachment":[{"name":"ae/aepng/gun_b/gun_b_00024"}]},"":{"attachment":[{"name":null}]}},"bones":{"gun_b":{"translate":[{"x":61.08,"y":29.09}]}}},"idle_18":{"slots":{"gun":{"attachment":[{"name":"ae/aepng/gun/gun_00023"}]},"gun_b":{"attachment":[{"name":"ae/aepng/gun_b/gun_b_00023"}]},"":{"attachment":[{"name":null}]}},"bones":{"gun_b":{"translate":[{"x":63.86,"y":37.79}]}}},"idle_19":{"slots":{"gun":{"attachment":[{"name":"ae/aepng/gun/gun_00022"}]},"gun_b":{"attachment":[{"name":"ae/aepng/gun_b/gun_b_00022"}]},"":{"attachment":[{"name":null}]}},"bones":{"gun_b":{"translate":[{"x":63.86,"y":46.55}]}}},"idle_20":{"slots":{"gun":{"attachment":[{"name":"ae/aepng/gun/gun_00021"}]},"gun_b":{"attachment":[{"name":"ae/aepng/gun_b/gun_b_00021"}]},"":{"attachment":[{"name":null}]}},"bones":{"gun_b":{"translate":[{"x":62.04,"y":55.67}]}}},"idle_21":{"slots":{"gun":{"attachment":[{"name":"ae/aepng/gun/gun_00020"}]},"gun_b":{"attachment":[{"name":"ae/aepng/gun_b/gun_b_00020"}]},"":{"attachment":[{"name":null}]}},"bones":{"gun_b":{"translate":[{"x":56.02,"y":63.33}]}}},"idle_22":{"slots":{"gun":{"attachment":[{"name":"ae/aepng/gun/gun_00019"}]},"gun_b":{"attachment":[{"name":"ae/aepng/gun_b/gun_b_00019"}]},"":{"attachment":[{"name":null}]}},"bones":{"gun_b":{"translate":[{"x":47.27,"y":69.35}]}}},"idle_23":{"slots":{"gun":{"attachment":[{"name":"ae/aepng/gun/gun_00018"}]},"gun_b":{"attachment":[{"name":"ae/aepng/gun_b/gun_b_00018"}]},"":{"attachment":[{"name":null}]}},"bones":{"gun_b":{"translate":[{"x":38.52,"y":77.01}]}}},"idle_24":{"slots":{"gun":{"attachment":[{"name":"ae/aepng/gun/gun_00017"}]},"gun_b":{"attachment":[{"name":"ae/aepng/gun_b/gun_b_00017"}]},"":{"attachment":[{"name":null}]}},"bones":{"gun_b":{"translate":[{"x":25.94,"y":81.38}]}}},"idle_25":{"slots":{"gun":{"attachment":[{"name":"ae/aepng/gun/gun_00016"}]},"gun_b":{"attachment":[{"name":"ae/aepng/gun_b/gun_b_00016"}]},"":{"attachment":[{"name":null}]}},"bones":{"gun_b":{"translate":[{"x":12.26,"y":83.02}]}}},"idle_26":{"slots":{"gun":{"attachment":[{"name":"ae/aepng/gun/gun_00015"}]},"gun_b":{"attachment":[{"name":"ae/aepng/gun_b/gun_b_00015"}]},"":{"attachment":[{"name":null}]}},"bones":{"gun_b":{"translate":[{"x":-0.87,"y":84.66}]}}},"idle_27":{"slots":{"gun":{"attachment":[{"name":"ae/aepng/gun/gun_00014"}]},"gun_b":{"attachment":[{"name":"ae/aepng/gun_b/gun_b_00014"}]},"":{"attachment":[{"name":null}]}},"bones":{"gun_b":{"translate":[{"x":-15.09,"y":86.31}]}}},"idle_28":{"slots":{"gun":{"attachment":[{"name":"ae/aepng/gun/gun_00013"}]},"gun_b":{"attachment":[{"name":"ae/aepng/gun_b/gun_b_00013"}]},"":{"attachment":[{"name":null}]}},"bones":{"gun_b":{"translate":[{"x":-27.67,"y":80.29}]}}},"idle_29":{"slots":{"gun":{"attachment":[{"name":"ae/aepng/gun/gun_00012"}]},"gun_b":{"attachment":[{"name":"ae/aepng/gun_b/gun_b_00012"}]},"":{"attachment":[{"name":null}]}},"bones":{"gun_b":{"translate":[{"x":-39.16,"y":76.46}]}}},"ready_0":{"slots":{"eff":{"attachment":[{"name":"eff/d01"},{"time":0.0333,"name":"eff/d02"},{"time":0.0667,"name":"eff/d03"},{"time":0.1,"name":"eff/d04"},{"time":0.1333,"name":null},{"time":0.1667,"name":"eff/d05"},{"time":0.2,"name":"eff/d06"},{"time":0.2333,"name":"eff/d01"}]},"gun":{"attachment":[{"name":"ae/aepng/gun/gun_00011"}]},"gun_b":{"attachment":[{"name":"ae/aepng/gun_b/gun_b_00011"}]},"":{"attachment":[{"name":null}]}},"bones":{"eff":{"translate":[{"x":-88.35,"y":124.23}]},"gun_b":{"translate":[{"x":-50.64,"y":70.99}]}}},"ready_1":{"slots":{"eff":{"attachment":[{"name":"eff/d01"},{"time":0.0333,"name":"eff/d02"},{"time":0.0667,"name":"eff/d03"},{"time":0.1,"name":"eff/d04"},{"time":0.1333,"name":null},{"time":0.1667,"name":"eff/d05"},{"time":0.2,"name":"eff/d06"},{"time":0.2333,"name":"eff/d01"}]},"gun":{"attachment":[{"name":"ae/aepng/gun/gun_00010"}]},"gun_b":{"attachment":[{"name":"ae/aepng/gun_b/gun_b_00010"}]},"":{"attachment":[{"name":null}]}},"bones":{"eff":{"translate":[{"x":-103.12,"y":114.93}]},"gun_b":{"translate":[{"x":-59.4,"y":64.43}]}}},"ready_2":{"slots":{"eff":{"attachment":[{"name":"eff/d01"},{"time":0.0333,"name":"eff/d02"},{"time":0.0667,"name":"eff/d03"},{"time":0.1,"name":"eff/d04"},{"time":0.1333,"name":null},{"time":0.1667,"name":"eff/d05"},{"time":0.2,"name":"eff/d06"},{"time":0.2333,"name":"eff/d01"}]},"gun":{"attachment":[{"name":"ae/aepng/gun/gun_00009"}]},"gun_b":{"attachment":[{"name":"ae/aepng/gun_b/gun_b_00009"}]},"":{"attachment":[{"name":null}]}},"bones":{"eff":{"translate":[{"x":-115.15,"y":99.07}]},"gun_b":{"translate":[{"x":-64.32,"y":55.67}]}}},"ready_3":{"slots":{"eff":{"attachment":[{"name":"eff/d01"},{"time":0.0333,"name":"eff/d02"},{"time":0.0667,"name":"eff/d03"},{"time":0.1,"name":"eff/d04"},{"time":0.1333,"name":null},{"time":0.1667,"name":"eff/d05"},{"time":0.2,"name":"eff/d06"},{"time":0.2333,"name":"eff/d01"}]},"gun":{"attachment":[{"name":"ae/aepng/gun/gun_00008"}]},"gun_b":{"attachment":[{"name":"ae/aepng/gun_b/gun_b_00008"}]},"":{"attachment":[{"name":null}]}},"bones":{"eff":{"translate":[{"x":-121.17,"y":84.85}]},"gun_b":{"translate":[{"x":-66.51,"y":47.47}]}}},"ready_4":{"slots":{"eff":{"attachment":[{"name":"eff/d01"},{"time":0.0333,"name":"eff/d02"},{"time":0.0667,"name":"eff/d03"},{"time":0.1,"name":"eff/d04"},{"time":0.1333,"name":null},{"time":0.1667,"name":"eff/d05"},{"time":0.2,"name":"eff/d06"},{"time":0.2333,"name":"eff/d01"}]},"gun":{"attachment":[{"name":"ae/aepng/gun/gun_00007"}]},"gun_b":{"attachment":[{"name":"ae/aepng/gun_b/gun_b_00007"}]},"":{"attachment":[{"name":null}]}},"bones":{"eff":{"translate":[{"x":-120.08,"y":66.79}]},"gun_b":{"translate":[{"x":-65.96,"y":37.62}]}}},"ready_5":{"slots":{"eff":{"attachment":[{"name":"eff/d01"},{"time":0.0333,"name":"eff/d02"},{"time":0.0667,"name":"eff/d03"},{"time":0.1,"name":"eff/d04"},{"time":0.1333,"name":null},{"time":0.1667,"name":"eff/d05"},{"time":0.2,"name":"eff/d06"},{"time":0.2333,"name":"eff/d01"}]},"gun":{"attachment":[{"name":"ae/aepng/gun/gun_00006"}]},"gun_b":{"attachment":[{"name":"ae/aepng/gun_b/gun_b_00006"}]},"":{"attachment":[{"name":null}]}},"bones":{"eff":{"translate":[{"x":-111.32,"y":52.02}]},"gun_b":{"translate":[{"x":-62.68,"y":30.51}]}}},"ready_6":{"slots":{"eff":{"attachment":[{"name":"eff/d01"},{"time":0.0333,"name":"eff/d02"},{"time":0.0667,"name":"eff/d03"},{"time":0.1,"name":"eff/d04"},{"time":0.1333,"name":null},{"time":0.1667,"name":"eff/d05"},{"time":0.2,"name":"eff/d06"},{"time":0.2333,"name":"eff/d01"}]},"gun":{"attachment":[{"name":"ae/aepng/gun/gun_00005"}]},"gun_b":{"attachment":[{"name":"ae/aepng/gun_b/gun_b_00005"}]},"":{"attachment":[{"name":null}]}},"bones":{"eff":{"translate":[{"x":-102.03,"y":37.26}]},"gun_b":{"translate":[{"x":-57.21,"y":21.76}]}}},"ready_7":{"slots":{"eff":{"attachment":[{"name":"eff/d01"},{"time":0.0333,"name":"eff/d02"},{"time":0.0667,"name":"eff/d03"},{"time":0.1,"name":"eff/d04"},{"time":0.1333,"name":null},{"time":0.1667,"name":"eff/d05"},{"time":0.2,"name":"eff/d06"},{"time":0.2333,"name":"eff/d01"}]},"gun":{"attachment":[{"name":"ae/aepng/gun/gun_00004"}]},"gun_b":{"attachment":[{"name":"ae/aepng/gun_b/gun_b_00004"}]},"":{"attachment":[{"name":null}]}},"bones":{"eff":{"translate":[{"x":-88.35,"y":25.77}]},"gun_b":{"translate":[{"x":-49,"y":15.19}]}}},"ready_8":{"slots":{"eff":{"attachment":[{"name":"eff/d01"},{"time":0.0333,"name":"eff/d02"},{"time":0.0667,"name":"eff/d03"},{"time":0.1,"name":"eff/d04"},{"time":0.1333,"name":null},{"time":0.1667,"name":"eff/d05"},{"time":0.2,"name":"eff/d06"},{"time":0.2333,"name":"eff/d01"}]},"gun":{"attachment":[{"name":"ae/aepng/gun/gun_00003"}]},"gun_b":{"attachment":[{"name":"ae/aepng/gun_b/gun_b_00003"}]},"":{"attachment":[{"name":null}]}},"bones":{"eff":{"translate":[{"x":-69.34,"y":15.29}]},"gun_b":{"translate":[{"x":-38.53,"y":8.6}]}}},"ready_9":{"slots":{"eff":{"attachment":[{"name":"eff/d01"},{"time":0.0333,"name":"eff/d02"},{"time":0.0667,"name":"eff/d03"},{"time":0.1,"name":"eff/d04"},{"time":0.1333,"name":null},{"time":0.1667,"name":"eff/d05"},{"time":0.2,"name":"eff/d06"},{"time":0.2333,"name":"eff/d01"}]},"gun":{"attachment":[{"name":"ae/aepng/gun/gun_00002"}]},"gun_b":{"attachment":[{"name":"ae/aepng/gun_b/gun_b_00002"}]}},"bones":{"eff":{"translate":[{"x":-48.48,"y":6.87}]},"gun_b":{"translate":[{"x":-27.55,"y":3.84}]}}},"ready_10":{"slots":{"eff":{"attachment":[{"name":"eff/d01"},{"time":0.0333,"name":"eff/d02"},{"time":0.0667,"name":"eff/d03"},{"time":0.1,"name":"eff/d04"},{"time":0.1333,"name":"eff/d05"},{"time":0.1667,"name":"eff/d06"},{"time":0.2,"name":"eff/d01"}]},"gun":{"attachment":[{"name":"ae/aepng/gun/gun_00001"}]},"gun_b":{"attachment":[{"name":"ae/aepng/gun_b/gun_b_00001"}]}},"bones":{"eff":{"translate":[{"x":-27.96,"y":6.14}]},"gun_b":{"translate":[{"x":-10.91,"y":2.73}]}}},"ready_11":{"slots":{"eff":{"attachment":[{"name":"eff/d01"},{"time":0.0333,"name":"eff/d02"},{"time":0.0667,"name":"eff/d03"},{"time":0.1,"name":"eff/d04"},{"time":0.1333,"name":"eff/d05"},{"time":0.1667,"name":"eff/d06"},{"time":0.2,"name":"eff/d01"}]}}},"ready_12":{"slots":{"eff":{"attachment":[{"name":"eff/d01"},{"time":0.0333,"name":"eff/d02"},{"time":0.0667,"name":"eff/d03"},{"time":0.1,"name":"eff/d04"},{"time":0.1333,"name":null},{"time":0.1667,"name":"eff/d05"},{"time":0.2,"name":"eff/d06"},{"time":0.2333,"name":"eff/d01"}]},"gun":{"attachment":[{"name":"ae/aepng/gun/gun_00029"}]},"gun_b":{"attachment":[{"name":"ae/aepng/gun_b/gun_b_00029"}]},"":{"attachment":[{"name":null}]}},"bones":{"eff":{"translate":[{"x":34.63,"y":5.61}]},"gun_b":{"translate":[{"x":13.12,"y":1.68}]}}},"ready_13":{"slots":{"eff":{"attachment":[{"name":"eff/d01"},{"time":0.0333,"name":"eff/d02"},{"time":0.0667,"name":"eff/d03"},{"time":0.1,"name":"eff/d04"},{"time":0.1333,"name":null},{"time":0.1667,"name":"eff/d05"},{"time":0.2,"name":"eff/d06"},{"time":0.2333,"name":"eff/d01"}]},"gun":{"attachment":[{"name":"ae/aepng/gun/gun_00028"}]},"gun_b":{"attachment":[{"name":"ae/aepng/gun_b/gun_b_00028"}]},"":{"attachment":[{"name":null}]}},"bones":{"eff":{"translate":[{"x":47.52,"y":7.12}]},"gun_b":{"translate":[{"x":25.15,"y":5.17}]}}},"ready_14":{"slots":{"eff":{"attachment":[{"name":"eff/d01"},{"time":0.0333,"name":"eff/d02"},{"time":0.0667,"name":"eff/d03"},{"time":0.1,"name":"eff/d04"},{"time":0.1333,"name":null},{"time":0.1667,"name":"eff/d05"},{"time":0.2,"name":"eff/d06"},{"time":0.2333,"name":"eff/d01"}]},"gun":{"attachment":[{"name":"ae/aepng/gun/gun_00027"}]},"gun_b":{"attachment":[{"name":"ae/aepng/gun_b/gun_b_00027"}]},"":{"attachment":[{"name":null}]}},"bones":{"eff":{"translate":[{"x":67.98,"y":13.95}]},"gun_b":{"translate":[{"x":37.28,"y":7.82}]}}},"ready_15":{"slots":{"eff":{"attachment":[{"name":"eff/d01"},{"time":0.0333,"name":"eff/d02"},{"time":0.0667,"name":"eff/d03"},{"time":0.1,"name":"eff/d04"},{"time":0.1333,"name":null},{"time":0.1667,"name":"eff/d05"},{"time":0.2,"name":"eff/d06"},{"time":0.2333,"name":"eff/d01"}]},"gun":{"attachment":[{"name":"ae/aepng/gun/gun_00026"}]},"gun_b":{"attachment":[{"name":"ae/aepng/gun_b/gun_b_00026"}]},"":{"attachment":[{"name":null}]}},"bones":{"eff":{"translate":[{"x":85.79,"y":24.56}]},"gun_b":{"translate":[{"x":48.27,"y":13.88}]}}},"ready_16":{"slots":{"eff":{"attachment":[{"name":"eff/d01"},{"time":0.0333,"name":"eff/d02"},{"time":0.0667,"name":"eff/d03"},{"time":0.1,"name":"eff/d04"},{"time":0.1333,"name":null},{"time":0.1667,"name":"eff/d05"},{"time":0.2,"name":"eff/d06"},{"time":0.2333,"name":"eff/d01"}]},"gun":{"attachment":[{"name":"ae/aepng/gun/gun_00025"}]},"gun_b":{"attachment":[{"name":"ae/aepng/gun_b/gun_b_00025"}]},"":{"attachment":[{"name":null}]}},"bones":{"eff":{"translate":[{"x":98.68,"y":37.44}]},"gun_b":{"translate":[{"x":55.09,"y":21.84}]}}},"ready_17":{"slots":{"eff":{"attachment":[{"name":"eff/d01"},{"time":0.0333,"name":"eff/d02"},{"time":0.0667,"name":"eff/d03"},{"time":0.1,"name":"eff/d04"},{"time":0.1333,"name":null},{"time":0.1667,"name":"eff/d05"},{"time":0.2,"name":"eff/d06"},{"time":0.2333,"name":"eff/d01"}]},"gun":{"attachment":[{"name":"ae/aepng/gun/gun_00024"}]},"gun_b":{"attachment":[{"name":"ae/aepng/gun_b/gun_b_00024"}]},"":{"attachment":[{"name":null}]}},"bones":{"eff":{"translate":[{"x":109.7,"y":51.62}]},"gun_b":{"translate":[{"x":61.08,"y":29.09}]}}},"ready_18":{"slots":{"eff":{"attachment":[{"name":"eff/d01"},{"time":0.0333,"name":"eff/d02"},{"time":0.0667,"name":"eff/d03"},{"time":0.1,"name":"eff/d04"},{"time":0.1333,"name":null},{"time":0.1667,"name":"eff/d05"},{"time":0.2,"name":"eff/d06"},{"time":0.2333,"name":"eff/d01"}]},"gun":{"attachment":[{"name":"ae/aepng/gun/gun_00023"}]},"gun_b":{"attachment":[{"name":"ae/aepng/gun_b/gun_b_00023"}]},"":{"attachment":[{"name":null}]}},"bones":{"eff":{"translate":[{"x":114.23,"y":66.58}]},"gun_b":{"translate":[{"x":63.86,"y":37.79}]}}},"ready_19":{"slots":{"eff":{"attachment":[{"name":"eff/d01"},{"time":0.0333,"name":"eff/d02"},{"time":0.0667,"name":"eff/d03"},{"time":0.1,"name":"eff/d04"},{"time":0.1333,"name":null},{"time":0.1667,"name":"eff/d05"},{"time":0.2,"name":"eff/d06"},{"time":0.2333,"name":"eff/d01"}]},"gun":{"attachment":[{"name":"ae/aepng/gun/gun_00022"}]},"gun_b":{"attachment":[{"name":"ae/aepng/gun_b/gun_b_00022"}]},"":{"attachment":[{"name":null}]}},"bones":{"eff":{"translate":[{"x":112.4,"y":83.37}]},"gun_b":{"translate":[{"x":63.86,"y":46.55}]}}},"ready_20":{"slots":{"eff":{"attachment":[{"name":"eff/d01"},{"time":0.0333,"name":"eff/d02"},{"time":0.0667,"name":"eff/d03"},{"time":0.1,"name":"eff/d04"},{"time":0.1333,"name":null},{"time":0.1667,"name":"eff/d05"},{"time":0.2,"name":"eff/d06"},{"time":0.2333,"name":"eff/d01"}]},"gun":{"attachment":[{"name":"ae/aepng/gun/gun_00021"}]},"gun_b":{"attachment":[{"name":"ae/aepng/gun_b/gun_b_00021"}]},"":{"attachment":[{"name":null}]}},"bones":{"eff":{"translate":[{"x":105.83,"y":96.88}]},"gun_b":{"translate":[{"x":62.04,"y":55.67}]}}},"ready_21":{"slots":{"eff":{"attachment":[{"name":"eff/d01"},{"time":0.0333,"name":"eff/d02"},{"time":0.0667,"name":"eff/d03"},{"time":0.1,"name":"eff/d04"},{"time":0.1333,"name":null},{"time":0.1667,"name":"eff/d05"},{"time":0.2,"name":"eff/d06"},{"time":0.2333,"name":"eff/d01"}]},"gun":{"attachment":[{"name":"ae/aepng/gun/gun_00020"}]},"gun_b":{"attachment":[{"name":"ae/aepng/gun_b/gun_b_00020"}]},"":{"attachment":[{"name":null}]}},"bones":{"eff":{"translate":[{"x":96.53,"y":108.37}]},"gun_b":{"translate":[{"x":56.02,"y":63.33}]}}},"ready_22":{"slots":{"eff":{"attachment":[{"name":"eff/d01"},{"time":0.0333,"name":"eff/d02"},{"time":0.0667,"name":"eff/d03"},{"time":0.1,"name":"eff/d04"},{"time":0.1333,"name":null},{"time":0.1667,"name":"eff/d05"},{"time":0.2,"name":"eff/d06"},{"time":0.2333,"name":"eff/d01"}]},"gun":{"attachment":[{"name":"ae/aepng/gun/gun_00019"}]},"gun_b":{"attachment":[{"name":"ae/aepng/gun_b/gun_b_00019"}]},"":{"attachment":[{"name":null}]}},"bones":{"eff":{"translate":[{"x":80.67,"y":119.31}]},"gun_b":{"translate":[{"x":47.27,"y":69.35}]}}},"ready_23":{"slots":{"eff":{"attachment":[{"name":"eff/d01"},{"time":0.0333,"name":"eff/d02"},{"time":0.0667,"name":"eff/d03"},{"time":0.1,"name":"eff/d04"},{"time":0.1333,"name":null},{"time":0.1667,"name":"eff/d05"},{"time":0.2,"name":"eff/d06"},{"time":0.2333,"name":"eff/d01"}]},"gun":{"attachment":[{"name":"ae/aepng/gun/gun_00018"}]},"gun_b":{"attachment":[{"name":"ae/aepng/gun_b/gun_b_00018"}]},"":{"attachment":[{"name":null}]}},"bones":{"eff":{"translate":[{"x":60.98,"y":132.43}]},"gun_b":{"translate":[{"x":38.52,"y":77.01}]}}},"ready_24":{"slots":{"eff":{"attachment":[{"name":"eff/d01"},{"time":0.0333,"name":"eff/d02"},{"time":0.0667,"name":"eff/d03"},{"time":0.1,"name":"eff/d04"},{"time":0.1333,"name":null},{"time":0.1667,"name":"eff/d05"},{"time":0.2,"name":"eff/d06"},{"time":0.2333,"name":"eff/d01"}]},"gun":{"attachment":[{"name":"ae/aepng/gun/gun_00017"}]},"gun_b":{"attachment":[{"name":"ae/aepng/gun_b/gun_b_00017"}]},"":{"attachment":[{"name":null}]}},"bones":{"eff":{"translate":[{"x":43.48,"y":140.09}]},"gun_b":{"translate":[{"x":25.94,"y":81.38}]}}},"ready_25":{"slots":{"eff":{"attachment":[{"name":"eff/d01"},{"time":0.0333,"name":"eff/d02"},{"time":0.0667,"name":"eff/d03"},{"time":0.1,"name":"eff/d04"},{"time":0.1333,"name":null},{"time":0.1667,"name":"eff/d05"},{"time":0.2,"name":"eff/d06"},{"time":0.2333,"name":"eff/d01"}]},"gun":{"attachment":[{"name":"ae/aepng/gun/gun_00016"}]},"gun_b":{"attachment":[{"name":"ae/aepng/gun_b/gun_b_00016"}]},"":{"attachment":[{"name":null}]}},"bones":{"eff":{"translate":[{"x":19.95,"y":145.01}]},"gun_b":{"translate":[{"x":12.26,"y":83.02}]}}},"ready_26":{"slots":{"eff":{"attachment":[{"name":"eff/d01"},{"time":0.0333,"name":"eff/d02"},{"time":0.0667,"name":"eff/d03"},{"time":0.1,"name":"eff/d04"},{"time":0.1333,"name":null},{"time":0.1667,"name":"eff/d05"},{"time":0.2,"name":"eff/d06"},{"time":0.2333,"name":"eff/d01"}]},"gun":{"attachment":[{"name":"ae/aepng/gun/gun_00015"}]},"gun_b":{"attachment":[{"name":"ae/aepng/gun_b/gun_b_00015"}]},"":{"attachment":[{"name":null}]}},"bones":{"eff":{"translate":[{"x":-2.1,"y":153.11}]},"gun_b":{"translate":[{"x":-0.87,"y":84.66}]}}},"ready_27":{"slots":{"eff":{"attachment":[{"name":"eff/d01"},{"time":0.0333,"name":"eff/d02"},{"time":0.0667,"name":"eff/d03"},{"time":0.1,"name":"eff/d04"},{"time":0.1333,"name":null},{"time":0.1667,"name":"eff/d05"},{"time":0.2,"name":"eff/d06"},{"time":0.2333,"name":"eff/d01"}]},"gun":{"attachment":[{"name":"ae/aepng/gun/gun_00014"}]},"gun_b":{"attachment":[{"name":"ae/aepng/gun_b/gun_b_00014"}]},"":{"attachment":[{"name":null}]}},"bones":{"eff":{"translate":[{"x":-26.54,"y":148.84}]},"gun_b":{"translate":[{"x":-15.09,"y":86.31}]}}},"ready_28":{"slots":{"eff":{"attachment":[{"name":"eff/d01"},{"time":0.0333,"name":"eff/d02"},{"time":0.0667,"name":"eff/d03"},{"time":0.1,"name":"eff/d04"},{"time":0.1333,"name":null},{"time":0.1667,"name":"eff/d05"},{"time":0.2,"name":"eff/d06"},{"time":0.2333,"name":"eff/d01"}]},"gun":{"attachment":[{"name":"ae/aepng/gun/gun_00013"}]},"gun_b":{"attachment":[{"name":"ae/aepng/gun_b/gun_b_00013"}]},"":{"attachment":[{"name":null}]}},"bones":{"eff":{"translate":[{"x":-50.06,"y":141.73}]},"gun_b":{"translate":[{"x":-27.67,"y":80.29}]}}},"ready_29":{"slots":{"eff":{"attachment":[{"name":"eff/d01"},{"time":0.0333,"name":"eff/d02"},{"time":0.0667,"name":"eff/d03"},{"time":0.1,"name":"eff/d04"},{"time":0.1333,"name":null},{"time":0.1667,"name":"eff/d05"},{"time":0.2,"name":"eff/d06"},{"time":0.2333,"name":"eff/d01"}]},"gun":{"attachment":[{"name":"ae/aepng/gun/gun_00012"}]},"gun_b":{"attachment":[{"name":"ae/aepng/gun_b/gun_b_00012"}]},"":{"attachment":[{"name":null}]}},"bones":{"eff":{"translate":[{"x":-68.66,"y":135.17}]},"gun_b":{"translate":[{"x":-39.16,"y":76.46}]}}}}}